logger/__init__.py
logger/config/__init__.py
logger/config/format.py
logger/config/logger.py
logger/manager/__init__.py
logger/manager/logger.py
com_terra_logger-0.1.0.dist-info/licenses/LICENSE
com_terra_logger-0.1.0.dist-info/METADATA
com_terra_logger-0.1.0.dist-info/WHEEL
com_terra_logger-0.1.0.dist-info/RECORD
