Metadata-Version: 2.4
Name: com-terra-logger
Version: 0.1.0
Summary: Reusable logger utility
License: MIT
License-File: LICENSE
Author: Telephone.com
Requires-Python: >=3.12,<4.0
Classifier: License :: OSI Approved :: MIT License
Classifier: Programming Language :: Python :: 3
Classifier: Programming Language :: Python :: 3.12
Classifier: Programming Language :: Python :: 3.13
Classifier: Programming Language :: Python :: 3.14
Requires-Dist: colorama (>=0.4.6,<0.5.0)
